poimage/__init__.py
poimage/api/__init__.py
poimage/api/image.py
poimage/core/ImageType.py
poimage/core/__init__.py
poimage/lib/__init__.py
poimage/lib/image/__init__.py
poimage/lib/image/add_watermark_service.py
poimage/lib/image/eliminate_background.py
poimage/src/imgs/1024.png
tests/__init__.py
tests/test.py
poimage-0.0.22.dist-info/LICENSE
poimage-0.0.22.dist-info/METADATA
poimage-0.0.22.dist-info/WHEEL
poimage-0.0.22.dist-info/top_level.txt
poimage-0.0.22.dist-info/RECORD
