Metadata-Version: 2.1
Name: poimage
Version: 0.0.22
Summary: pip install poimage
Home-page: https://www.python-office.com/
Author: CoderWanFeng
Author-email: 1957875073@qq.com
License: MIT
Project-URL: Bug Tracker, https://github.com/CoderWanFeng/poimage/issues
Project-URL: Documentation, https://github.com/CoderWanFeng/poimage/blob/master/README.md
Project-URL: Source Code, https://github.com/CoderWanFeng/poimage
Platform: any
Requires-Python: >=3.7
License-File: LICENSE
Requires-Dist: pillow
Requires-Dist: alive-progress
Requires-Dist: requests
Requires-Dist: wordcloud
Requires-Dist: jieba
Requires-Dist: opencv-python
Requires-Dist: pofile
